mathxyz/__init__.py
mathxyz/core.py
mathxyz-0.1.0.dist-info/LICENSE
mathxyz-0.1.0.dist-info/METADATA
mathxyz-0.1.0.dist-info/WHEEL
mathxyz-0.1.0.dist-info/top_level.txt
mathxyz-0.1.0.dist-info/RECORD
