Metadata-Version: 2.1
Name: mathxyz
Version: 0.1.0
Summary: A state-of-the-art math solver library using advanced symbolic, numerical.
Home-page: https://github.com/mr-r0ot/mathxyz
Author: Muhammad Taha Gorji
Author-email: MohammadTahaGorjiProfile@gmail.com
Classifier: Programming Language :: Python :: 3
Classifier: License :: OSI Approved :: MIT License
Classifier: Operating System :: OS Independent
Requires-Python: >=3.6
License-File: LICENSE
Requires-Dist: numpy
Requires-Dist: sympy
